example_decrypt.py
example_encrypt.py
example_message.py
simple2encrypt.py
simple2encrypt-1.5.8.dist-info/LICENSE
simple2encrypt-1.5.8.dist-info/METADATA
simple2encrypt-1.5.8.dist-info/WHEEL
simple2encrypt-1.5.8.dist-info/entry_points.txt
simple2encrypt-1.5.8.dist-info/top_level.txt
simple2encrypt-1.5.8.dist-info/RECORD
