Metadata-Version: 2.1
Name: simple2encrypt
Version: 1.5.8
Summary: Utility functions for encryption and file operations
Home-page: https://github.com/nhman-python/crypto-utils
Author: nhman-python
Author-email: wbgblfix@duck.com
License: MIT
License-File: LICENSE
Requires-Dist: pycryptodome
